ciffy/__init__.py
ciffy/enum.py
ciffy/main.py
ciffy/reduction.py
ciffy/src/_ciffy_c.c
ciffy/src/_ciffy_c.h
ciffy/src/cif.c
ciffy/src/cif.h
ciffy/src/hash/atom.c
ciffy/src/hash/element.c
ciffy/src/hash/lookup.h
ciffy/src/hash/residue.c
ciffy/src/io.c
ciffy/src/io.h
ciffy/src/py.c
ciffy/src/py.h
ciffy-0.1.1.dist-info/LICENSE.md
ciffy-0.1.1.dist-info/METADATA
ciffy-0.1.1.dist-info/WHEEL
ciffy-0.1.1.dist-info/RECORD
